minibook/__init__.py
minibook/exceptions.py
minibook/main.py
minibook/plugins.py
minibook/py.typed
minibook/utils.py
minibook/templates/bare.j2
minibook/templates/html.j2
minibook-1.3.2.dist-info/METADATA
minibook-1.3.2.dist-info/WHEEL
minibook-1.3.2.dist-info/entry_points.txt
minibook-1.3.2.dist-info/licenses/LICENSE
minibook-1.3.2.dist-info/RECORD
