Metadata-Version: 2.4
Name: minibook
Version: 1.3.2
Summary: A simple tool for creating beautiful minibooks from a list of links
Project-URL: Homepage, https://tschm.github.io/minibook/
Project-URL: Documentation, https://tschm.github.io/minibook/
Project-URL: Repository, https://github.com/tschm/minibook
Project-URL: Source Code, https://github.com/tschm/minibook
Project-URL: Bug Tracker, https://github.com/tschm/minibook/issues
Project-URL: Discussions, https://github.com/tschm/minibook/discussions
Project-URL: Changelog, https://github.com/tschm/minibook/releases
Author-email: Thomas Schmelzer <thomas.schmelzer@gmail.com>
License: MIT
License-File: LICENSE
Keywords: documentation,generator,html,jinja2,links,minibook,reporting,static-site
Classifier: Development Status :: 5 - Production/Stable
Classifier: Intended Audience :: Developers
Classifier: License :: OSI Approved :: MIT License
Classifier: Operating System :: OS Independent
Classifier: Programming Language :: Python :: 3
Classifier: Programming Language :: Python :: 3.11
Classifier: Programming Language :: Python :: 3.12
Classifier: Programming Language :: Python :: 3.13
Classifier: Programming Language :: Python :: 3.14
Classifier: Topic :: Documentation
Classifier: Topic :: Internet :: WWW/HTTP :: Dynamic Content
Classifier: Topic :: Software Development :: Documentation
Classifier: Topic :: Text Processing :: Markup :: HTML
Classifier: Typing :: Typed
Requires-Python: >=3.11
Requires-Dist: jinja2<5.0,>=3.1.6
Requires-Dist: requests<3.0,>=2.31.0
Requires-Dist: typer<1.0,>=0.16.0
Provides-Extra: all
Requires-Dist: ebooklib>=0.18; extra == 'all'
Requires-Dist: fpdf2>=2.8.5; extra == 'all'
Provides-Extra: epub
Requires-Dist: ebooklib>=0.18; extra == 'epub'
Provides-Extra: pdf
Requires-Dist: fpdf2>=2.8.5; extra == 'pdf'
